AmazonSmartScraper/__init__.py
AmazonSmartScraper/config.py
AmazonSmartScraper/log_config.py
AmazonSmartScraper/scraper.py
AmazonSmartScraper/version.py
AmazonSmartScraper/helpers/__init__.py
AmazonSmartScraper/helpers/session_builder.py
AmazonSmartScraper/managers/__init__.py
AmazonSmartScraper/managers/fetcher.py
AmazonSmartScraper/managers/parser.py
AmazonSmartScraper/managers/proxy.py
AmazonSmartScraper/managers/session.py
AmazonSmartScraper/schemas/__init__.py
AmazonSmartScraper/schemas/custom_errors.py
AmazonSmartScraper/schemas/product.py
AmazonSmartScraper-1.1.1.dist-info/METADATA
AmazonSmartScraper-1.1.1.dist-info/WHEEL
AmazonSmartScraper-1.1.1.dist-info/top_level.txt
AmazonSmartScraper-1.1.1.dist-info/RECORD
