Metadata-Version: 2.1
Name: AmazonSmartScraper
Version: 1.1.1
Summary: A package to scrape Amazon product information
Home-page: https://github.com/mohammedbenserya/AmazonScraper
Author: BENSERYA Mohamed
Author-email: benseryamohammed1@gmail.com
Classifier: Programming Language :: Python :: 3
Classifier: License :: OSI Approved :: MIT License
Classifier: Operating System :: OS Independent
Requires-Python: >=3.10
Requires-Dist: pydantic
Requires-Dist: requests
Requires-Dist: bs4
Requires-Dist: selenium
Requires-Dist: webdriver-manager
Requires-Dist: fake-useragent
Requires-Dist: pyvirtualdisplay
Requires-Dist: lxml
Requires-Dist: python-decouple
Requires-Dist: colorlog
Requires-Dist: pyfiglet
